lynisParser/__init__.py
lynisParser-0.1.1.dist-info/DESCRIPTION.rst
lynisParser-0.1.1.dist-info/METADATA
lynisParser-0.1.1.dist-info/RECORD
lynisParser-0.1.1.dist-info/WHEEL
lynisParser-0.1.1.dist-info/metadata.json
lynisParser-0.1.1.dist-info/top_level.txt
