Metadata-Version: 2.0
Name: lynisParser
Version: 0.1.1
Summary: Parse Lynis report issues into lists of dictionaries
Home-page: https://github.com/GoVanguard/lynisParser
Author: Shane Scott
Author-email: sscott@gvit.com
License: UNKNOWN
Platform: UNKNOWN
Classifier: Development Status :: 3 - Alpha
Classifier: Intended Audience :: Developers
Classifier: License :: OSI Approved :: GNU General Public License v2 (GPLv2)
Classifier: Programming Language :: Python :: 3.6
Classifier: Operating System :: OS Independent
